README.md
setup.cfg
setup.py
django_rest_webhooks/__init__.py
django_rest_webhooks/admin.py
django_rest_webhooks/apps.py
django_rest_webhooks/client.py
django_rest_webhooks/config.py
django_rest_webhooks/models.py
django_rest_webhooks/signals.py
django_rest_webhooks/tasks.py
django_rest_webhooks/tests.py
django_rest_webhooks/utils.py
django_rest_webhooks.egg-info/PKG-INFO
django_rest_webhooks.egg-info/SOURCES.txt
django_rest_webhooks.egg-info/dependency_links.txt
django_rest_webhooks.egg-info/requires.txt
django_rest_webhooks.egg-info/top_level.txt
django_rest_webhooks/migrations/0001_initial.py
django_rest_webhooks/migrations/0002_swappable_hook_model.py
django_rest_webhooks/migrations/__init__.py