Metadata-Version: 2.1
Name: django-rest-webhooks
Version: 0.0.1
Summary: A powerful mechanism for sending real time API notifications via a new subscription model.
Home-page: https://github.com/leanrank/django-web-hooks
Author: Bohdan Datsko
Author-email: bohdan.datsko8888@gmail.com
License: UNKNOWN
Platform: UNKNOWN
Classifier: Development Status :: 5 - Production/Stable
Classifier: Environment :: Web Environment
Classifier: Framework :: Django
Classifier: Intended Audience :: Developers
Classifier: License :: OSI Approved :: BSD License
Classifier: Operating System :: OS Independent
Classifier: Programming Language :: Python
Classifier: Programming Language :: Python :: 2
Classifier: Programming Language :: Python :: 3
Classifier: Topic :: Utilities
